{
  "flair_0": [
    "France.",
    "Canada",
    "Nouvelle-Fance.",
    "Anglais.",
    "Frunce.",
    "Canada",
    "nLA",
    "Nouvelle-France",
    "baie",
    "golfe",
    "Nouvelle-Orleans.",
    "la"
  ],
  "flair_1": [
    "Canada",
    "du",
    "Francais.",
    "Nirginie",
    "Indiens"
  ],
  "flair_2": [
    "Canadiens",
    "Virginie",
    "1'Ohio",
    "1'Ohio",
    "Francais.",
    "Pittsbourg",
    "Etats-Unis"
  ],
  "flair_3": [
    "Canadiens",
    "Canadien",
    "Canadien"
  ],
  "flair_4": [
    "Canadien",
    "Jumonville"
  ],
  "flair_5": [
    "A",
    "Bois-Arbres",
    "Canadien"
  ],
  "flair_6": [
    "Canadien",
    "Canadien",
    "Quebec"
  ],
  "flair_7": [
    "Amerique",
    "Canadien",
    "Amerique",
    "Canadien"
  ],
  "flair_8": [],
  "flair_9": [
    "Notre",
    "Canadien"
  ],
  "flair_10": [
    "Indien"
  ],
  "flair_11": [
    "Peaux-Rouges.",
    "nLA",
    "Indien",
    "Canadien",
    "Canadien."
  ],
  "flair_12": [
    "Oi",
    "RIVIEIE",
    "Francais."
  ],
  "flair_13": [
    "Indiens",
    "Ilelle-RRiviere",
    "Indiens",
    "Virginie."
  ],
  "flair_14": [
    "I"
  ],
  "flair_15": [
    "Amerique.",
    "Amerique"
  ],
  "flair_16": [
    "Anglais",
    "Francais",
    "Americains"
  ],
  "flair_17": [],
  "flair_18": [],
  "flair_19": [
    "Leu",
    "Virginie"
  ],
  "flair_20": [],
  "flair_21": [
    "Amerique"
  ],
  "flair_22": [],
  "flair_23": [],
  "flair_24": [
    "Indiens",
    "Indiens",
    "Indiens"
  ],
  "flair_25": [
    "Yankees",
    "Indiens",
    "Nouveau-Monde",
    "du",
    "Canadien"
  ],
  "flair_26": [
    "Anglais",
    "France.",
    "la"
  ],
  "flair_27": [
    "Indiens",
    "Indiens"
  ],
  "flair_28": [
    "Canadien",
    "Canadien"
  ],
  "flair_29": [
    "IELLE",
    "1'Amerique",
    "Belle",
    "Canada",
    "France.",
    "1Ohio",
    "Mississipi",
    "Indiens"
  ],
  "flair_30": [
    "Indiens",
    "Duqueshe",
    "RIVIEE",
    "OQuoique"
  ],
  "flair_31": [
    "1'Elle"
  ],
  "flair_32": [],
  "flair_33": [
    "Dieppe",
    "Caen",
    "Vire"
  ],
  "flair_34": [],
  "flair_35": [],
  "flair_36": [
    "B"
  ],
  "flair_37": [
    "nA",
    "nA"
  ],
  "flair_38": [
    "Versailles",
    "nLA",
    "Canadienne",
    "Indien."
  ],
  "flair_39": [
    "Indiens",
    "nA",
    "Francais."
  ],
  "flair_40": [
    "Peaux-Rouges",
    "Indien."
  ],
  "flair_41": [
    "Peaux-Rouges"
  ],
  "flair_42": [
    "Oi"
  ],
  "flair_43": [],
  "flair_44": [
    "Canadienne",
    "Canadienne",
    "Rameau-d'Or"
  ],
  "flair_45": [
    "Canadienne"
  ],
  "flair_46": [
    "Canadienne"
  ],
  "flair_47": [],
  "flair_48": [],
  "flair_49": [
    "Canadienne",
    "Ol",
    "Canadienne"
  ],
  "flair_50": [
    "A",
    "Canadienne",
    "1'innocence"
  ],
  "flair_51": [],
  "flair_52": [
    "Canadienne"
  ],
  "flair_53": [],
  "flair_54": [],
  "flair_55": [
    "nLA",
    "l'Anjou",
    "Frangais",
    "l'Allehany",
    "Manongahela",
    "Marches",
    "Jerusalem",
    "Europe",
    "Sicile",
    "lerre",
    "Nouvelle-France",
    "Canada.",
    "1'epoque"
  ],
  "flair_56": [
    "Canada.",
    "BELLE",
    "Paris",
    "Ame",
    "au",
    "Nouvelle-France.",
    "Versailles"
  ],
  "flair_57": [
    "Versailles",
    "roi",
    "Paris"
  ],
  "flair_58": [
    "Quebec.",
    "capitale"
  ],
  "flair_59": [],
  "flair_60": [],
  "flair_61": [
    "Canadien"
  ],
  "flair_62": [],
  "flair_63": [
    "Nouvelle-France"
  ],
  "flair_64": [
    "Quebec",
    "Riviere",
    "Quebec"
  ],
  "flair_65": [
    "Versailles"
  ],
  "flair_66": [],
  "flair_67": [
    "A",
    "Canadienne."
  ],
  "flair_68": [
    "d'Ange",
    "Canadiens"
  ],
  "flair_69": [
    "A",
    "d'Ange",
    "A",
    "Canadiens",
    "I"
  ],
  "flair_70": [
    "nLA"
  ],
  "flair_71": [],
  "flair_72": [
    "Indiens"
  ],
  "flair_73": [
    "BELLE"
  ],
  "flair_74": [
    "Canadiens"
  ],
  "flair_75": [
    "I",
    "BELLE",
    "Iort",
    "Quebec"
  ],
  "flair_76": [
    "Villiers.",
    "Grigny",
    "Guyenne",
    "Quebec",
    "Gigny"
  ],
  "flair_77": [
    "I",
    "Quebec",
    "Grigny"
  ],
  "flair_78": [
    "nLA"
  ],
  "flair_79": [
    "I"
  ],
  "flair_80": [],
  "flair_81": [
    "Europe",
    "Ameique",
    "A"
  ],
  "flair_82": [],
  "flair_83": [
    "Canada",
    "Nouvelle-France",
    "Anglais."
  ],
  "flair_84": [
    "Europe",
    "Versailles"
  ],
  "flair_85": [
    "Francais"
  ],
  "flair_86": [
    "Or"
  ],
  "flair_87": [
    "Nouvelle-France"
  ],
  "flair_88": [
    "Amerique",
    "Quebec",
    "Peaux-Rouges"
  ],
  "flair_89": [
    "d'Ange"
  ],
  "flair_90": [],
  "flair_91": [
    "Versailles"
  ],
  "flair_92": [
    "Canadien"
  ],
  "flair_93": [
    "Canadien"
  ],
  "flair_94": [],
  "flair_95": [
    "Canadien"
  ],
  "flair_96": [],
  "flair_97": [],
  "flair_98": [
    "Louisiane"
  ],
  "flair_99": [
    "Alleghany",
    "Manangahela",
    "Yirginie",
    "Francais"
  ],
  "flair_100": [
    "la",
    "la",
    "Virginie",
    "nLA",
    "Francais"
  ],
  "flair_101": [
    "New-Yorl",
    "Canada",
    "Guyenne",
    "lBelle-Riviere",
    "lFrangais",
    "Canadien"
  ],
  "flair_102": [
    "nLA",
    "Guyenne.",
    "nA"
  ],
  "flair_103": [
    "nLA",
    "Guyenne.",
    "Canadien"
  ],
  "flair_104": [
    "Indiens",
    "Peaux-Rouges",
    "Canadien"
  ],
  "flair_105": [
    "Canadien"
  ],
  "flair_106": [
    "baie",
    "Or",
    "Nord",
    "Indi"
  ],
  "flair_107": [
    "Virginie",
    "nLA"
  ],
  "flair_108": [
    "Canadien",
    "Guyenne",
    "Grigny",
    "nC",
    "I"
  ],
  "flair_109": [
    "nLA",
    "RIVIERE",
    "Contreceur",
    "Grigny",
    "Guyenne"
  ],
  "flair_110": [],
  "flair_111": [],
  "flair_112": [
    "Guyenne",
    "Paris",
    "Dieppe",
    "Nouvelle-Fance"
  ],
  "flair_113": [
    "Europe",
    "Quebec",
    "Montreal"
  ],
  "flair_114": [
    "Grigny",
    "Bordeaux",
    "Versailles",
    "E"
  ],
  "flair_115": [
    "Canadien",
    "Francais",
    "France"
  ],
  "flair_116": [
    "Ehl",
    "Guyenne",
    "Indiens"
  ],
  "flair_117": [],
  "flair_118": [],
  "flair_119": [
    "Indiens",
    "E",
    "E"
  ],
  "flair_120": [],
  "flair_121": [],
  "flair_122": [
    "IIVIERE",
    "SIILOUEIE",
    "COUPE-AUTRE1S",
    "Grigny",
    "Grigny"
  ],
  "flair_123": [
    "A"
  ],
  "flair_124": [
    "A",
    "Sire"
  ],
  "flair_125": [
    "I"
  ],
  "flair_126": [],
  "flair_127": [
    "A",
    "Ouel"
  ],
  "flair_128": [],
  "flair_129": [
    "E",
    "Canadienne"
  ],
  "flair_130": [],
  "flair_131": [],
  "flair_132": [],
  "flair_133": [],
  "flair_134": [],
  "flair_135": [],
  "flair_136": [],
  "flair_137": [],
  "flair_138": [],
  "flair_139": [],
  "flair_140": [],
  "flair_141": [
    "Anglais2"
  ],
  "flair_142": [
    "nLA"
  ],
  "flair_143": [],
  "flair_144": [],
  "flair_145": [],
  "flair_146": [
    "Marigots",
    "Canadien"
  ],
  "flair_147": [
    "Marigots."
  ],
  "flair_148": [
    "Grigny",
    "nC"
  ],
  "flair_149": [],
  "flair_150": [
    "A",
    "Saint-Laurent."
  ],
  "flair_151": [
    "L'est",
    "cap",
    "cap",
    "cap",
    "Saint-Laurent",
    "Saint-Laurent"
  ],
  "flair_152": [
    "E",
    "Saint-lLauent",
    "Montmorency",
    "1'epoque",
    "Iace",
    "Montmorency"
  ],
  "flair_153": [
    "Quebec"
  ],
  "flair_154": [
    "Venise."
  ],
  "flair_155": [
    "I"
  ],
  "flair_156": [],
  "flair_157": [
    "Quebec",
    "A"
  ],
  "flair_158": [
    "E"
  ],
  "flair_159": [],
  "flair_160": [],
  "flair_161": [
    "France"
  ],
  "flair_162": [
    "Poitou",
    "Versailles",
    "nLA",
    "Paris",
    "Commercy",
    "Paris"
  ],
  "flair_163": [],
  "flair_164": [
    "IV1EnTRE"
  ],
  "flair_165": [
    "Les",
    "nLA"
  ],
  "flair_166": [],
  "flair_167": [],
  "flair_168": [
    "A",
    "IIRE"
  ],
  "flair_169": [
    "RIVIERE"
  ],
  "flair_170": [
    "E"
  ],
  "flair_171": [
    "Cette"
  ],
  "flair_172": [],
  "flair_173": [],
  "flair_174": [
    "Oi"
  ],
  "flair_175": [
    "Cette",
    "Les"
  ],
  "flair_176": [],
  "flair_177": [],
  "flair_178": [],
  "flair_179": [],
  "flair_180": [
    "I"
  ],
  "flair_181": [
    "Cette",
    "I"
  ],
  "flair_182": [
    "Oze"
  ],
  "flair_183": [
    "I"
  ],
  "flair_184": [],
  "flair_185": [
    "Grigny",
    "Aives"
  ],
  "flair_186": [
    "A"
  ],
  "flair_187": [
    "Cet",
    "In"
  ],
  "flair_188": [
    "A"
  ],
  "flair_189": [
    "I",
    "I"
  ],
  "flair_190": [],
  "flair_191": [
    "Les",
    "Ph"
  ],
  "flair_192": [],
  "flair_193": [
    "J'avais",
    "Versailles"
  ],
  "flair_194": [
    "la"
  ],
  "flair_195": [
    "la",
    "Canada",
    "Versailles"
  ],
  "flair_196": [],
  "flair_197": [
    "nLE",
    "Grigny"
  ],
  "flair_198": [
    "E",
    "nLA",
    "IVIERE"
  ],
  "flair_199": [
    "Peaux-Rouges",
    "E"
  ],
  "flair_200": [],
  "flair_201": [],
  "flair_202": [
    "Peaux-Rouges.",
    "Indien",
    "L'habitude",
    "Iais"
  ],
  "flair_203": [
    "Indiens"
  ],
  "flair_204": [
    "nLA",
    "RIVIRE",
    "Francais"
  ],
  "flair_205": [],
  "flair_206": [],
  "flair_207": [
    "Canadien"
  ],
  "flair_208": [
    "Amerique",
    "Franais"
  ],
  "flair_209": [
    "SIRE"
  ],
  "flair_210": [
    "Indiens",
    "I",
    "Amerique",
    "Canadien",
    "A"
  ],
  "flair_211": [
    "nLA",
    "RIV1",
    "Hors"
  ],
  "flair_212": [
    "Francais",
    "nLA",
    "Ehl"
  ],
  "flair_213": [
    "Indiens",
    "Indiens",
    "Canadien",
    "Indiens"
  ],
  "flair_214": [
    "Indiens",
    "Canadiens",
    "Amerique",
    "la"
  ],
  "flair_215": [
    "nLA",
    "A"
  ],
  "flair_216": [
    "Grigny",
    "A"
  ],
  "flair_217": [
    "A",
    "I"
  ],
  "flair_218": [
    "BELLE",
    "nLA",
    "RIVIERE"
  ],
  "flair_219": [],
  "flair_220": [
    "nII"
  ],
  "flair_221": [
    "A"
  ],
  "flair_222": [
    "Dites-moi"
  ],
  "flair_223": [
    "E"
  ],
  "flair_224": [
    "nLA"
  ],
  "flair_225": [],
  "flair_226": [],
  "flair_227": [],
  "flair_228": [],
  "flair_229": [],
  "flair_230": [
    "nLA"
  ],
  "flair_231": [],
  "flair_232": [],
  "flair_233": [],
  "flair_234": [
    "P",
    "Grigny",
    "Indiens"
  ],
  "flair_235": [
    "Canadiens.",
    "nA"
  ],
  "flair_236": [
    "Peaux-Rouges.",
    "nLA",
    "RIVIERE",
    "du",
    "Indiens"
  ],
  "flair_237": [
    "Indiens",
    "Teocalis",
    "Mexique",
    "Chichimeques"
  ],
  "flair_238": [
    "Cholula"
  ],
  "flair_239": [
    "nLE"
  ],
  "flair_240": [
    "nLA",
    "Totem",
    "Indiens",
    "Peaux-Rouges",
    "Indiens"
  ],
  "flair_241": [
    "Amerique",
    "Francais",
    "Indiens"
  ],
  "flair_242": [
    "Grigny",
    "Canadien"
  ],
  "flair_243": [],
  "flair_244": [
    "Canadien",
    "Francais"
  ],
  "flair_245": [],
  "flair_246": [
    "Indiens"
  ],
  "flair_247": [],
  "flair_248": [],
  "flair_249": [],
  "flair_250": [],
  "flair_251": [],
  "flair_252": [],
  "flair_253": [
    "Peaux-Rouges"
  ],
  "flair_254": [
    "Visages-Ples",
    "Visages-Pales",
    "Peaux-Rouges2",
    "Indies",
    "Indien",
    "Indiens"
  ],
  "flair_255": [
    "Indiens",
    "Peaux-Rouges",
    "Francais",
    "Indiens"
  ],
  "flair_256": [
    "Indiens",
    "A",
    "Francais",
    "Peaux-Rouges",
    "Indiens"
  ],
  "flair_257": [],
  "flair_258": [
    "Washington",
    "Virginie",
    "IBelle",
    "W",
    "Amerique"
  ],
  "flair_259": [
    "Anglais.",
    "Virginie",
    "Irancais"
  ],
  "flair_260": [],
  "flair_261": [
    "Vois"
  ],
  "flair_262": [],
  "flair_263": [],
  "flair_264": [],
  "flair_265": [
    "BEILLE"
  ],
  "flair_266": [
    "Les",
    "Washington"
  ],
  "flair_267": [],
  "flair_268": [
    "nLA",
    "Quelles",
    "L'officier",
    "Indiens"
  ],
  "flair_269": [],
  "flair_270": [
    "E"
  ],
  "flair_271": [
    "Indiens",
    "Indien",
    "1'Europe"
  ],
  "flair_272": [
    "Londres"
  ],
  "flair_273": [
    "Indiens."
  ],
  "flair_274": [
    "Indiens"
  ],
  "flair_275": [],
  "flair_276": [],
  "flair_277": [
    "Cette"
  ],
  "flair_278": [],
  "flair_279": [],
  "flair_280": [
    "Couleuvre"
  ],
  "flair_281": [
    "I",
    "Indiens."
  ],
  "flair_282": [
    "nA"
  ],
  "flair_283": [
    "IFrancaises",
    "Irancais",
    "Andel"
  ],
  "flair_284": [
    "Indiens",
    "Indiens"
  ],
  "flair_285": [
    "Indiens"
  ],
  "flair_286": [
    "Indiens"
  ],
  "flair_287": [],
  "flair_288": [],
  "flair_289": [],
  "flair_290": [
    "E",
    "II",
    "nII",
    "C",
    "I",
    "nLA"
  ],
  "flair_291": [],
  "flair_292": [],
  "flair_293": [
    "Indiens",
    "Canadiens"
  ],
  "flair_294": [
    "Europe"
  ],
  "flair_295": [
    "Canadien"
  ],
  "flair_296": [
    "Canadien"
  ],
  "flair_297": [
    "Canadien"
  ],
  "flair_298": [
    "Francais",
    "IEn",
    "Indiens"
  ],
  "flair_299": [
    "Indiens",
    "Indiens"
  ],
  "flair_300": [
    "Indiens"
  ],
  "flair_301": [],
  "flair_302": [
    "nA",
    "Indiens",
    "Peaux-Rouges"
  ],
  "flair_303": [
    "Amerique"
  ],
  "flair_304": [
    "nLA"
  ],
  "flair_305": [],
  "flair_306": [
    "Canadien"
  ],
  "flair_307": [
    "Canadien"
  ],
  "flair_308": [
    "Indiens",
    "O"
  ],
  "flair_309": [
    "Indiens",
    "Canadien"
  ],
  "flair_310": [
    "A",
    "Iit",
    "Indiens"
  ],
  "flair_311": [
    "Grigny"
  ],
  "flair_312": [],
  "flair_313": [],
  "flair_314": [
    "Canadien",
    "Indiens.",
    "Canadien"
  ],
  "flair_315": [
    "Francais"
  ],
  "flair_316": [
    "IL",
    "nLa",
    "Ioissements"
  ],
  "flair_317": [],
  "flair_318": [
    "AH",
    "I"
  ],
  "flair_319": [
    "Les"
  ],
  "flair_320": [
    "Indiens",
    "Les"
  ],
  "flair_321": [
    "Sans-Piste",
    "Bois",
    "I"
  ],
  "flair_322": [
    "G",
    "A",
    "Vingt-cinq"
  ],
  "flair_323": [],
  "flair_324": [
    "Canadien"
  ],
  "flair_325": [],
  "flair_326": [
    "P",
    "Canadien"
  ],
  "flair_327": [
    "Bois-Arbres"
  ],
  "flair_328": [
    "Eu"
  ],
  "flair_329": [],
  "flair_330": [
    "ILes",
    "Les",
    "Angele"
  ],
  "flair_331": [],
  "flair_332": [
    "Les",
    "F"
  ],
  "flair_333": [
    "ANGELE"
  ],
  "flair_334": [
    "Belle-Olivier",
    "Indiens"
  ],
  "flair_335": [
    "Indiens"
  ],
  "flair_336": [],
  "flair_337": [
    "Indiens"
  ],
  "flair_338": [
    "Belle-Olivier.",
    "Canadien"
  ],
  "flair_339": [
    "Anglais",
    "I"
  ],
  "flair_340": [
    "Canadien",
    "O",
    "Canadien"
  ],
  "flair_341": [
    "I"
  ],
  "flair_342": [
    "Indiens",
    "Indiens",
    "F"
  ],
  "flair_343": [],
  "flair_344": [
    "Canadien",
    "Indiens",
    "Les"
  ],
  "flair_345": [
    "Les",
    "Les",
    "Les"
  ],
  "flair_346": [
    "Indien"
  ],
  "flair_347": [],
  "flair_348": [
    "Rameau-d'O",
    "Gigny",
    "Cette"
  ],
  "flair_349": [
    "Gigny"
  ],
  "flair_350": [],
  "flair_351": [],
  "flair_352": [],
  "flair_353": [],
  "flair_354": [
    "Canadien"
  ],
  "flair_355": [
    "Grigny",
    "Canadien",
    "Canadien"
  ],
  "flair_356": [
    "Franais",
    "Canadien"
  ],
  "flair_357": [
    "Francais",
    "Les"
  ],
  "flair_358": [
    "Chteaux",
    "F",
    "nLA",
    "Canadien",
    "DANS",
    "Canada.",
    "Canada",
    "Indiens"
  ],
  "flair_359": [
    "\\",
    "Grigny",
    "Canadien"
  ],
  "flair_360": [
    "Canadien",
    "Indiens",
    "E"
  ],
  "flair_361": [
    "Or"
  ],
  "flair_362": [
    "Avant"
  ],
  "flair_363": [
    "Francais"
  ],
  "flair_364": [
    "Canadien"
  ],
  "flair_365": [
    "I",
    "Canadien",
    "Canadien",
    "Canadien.",
    "Francais"
  ],
  "flair_366": [],
  "flair_367": [],
  "flair_368": [
    "Indiens"
  ],
  "flair_369": [],
  "flair_370": [],
  "flair_371": [
    "Quelles",
    "Cette"
  ],
  "flair_372": [],
  "flair_373": [],
  "flair_374": [
    "Les"
  ],
  "flair_375": [],
  "flair_376": [
    "nA",
    "Cette"
  ],
  "flair_377": [
    "A"
  ],
  "flair_378": [
    "Peaux-ouest."
  ],
  "flair_379": [
    "Indiens.",
    "Indiens",
    "1'Amrique",
    "Indiens",
    "Indiens"
  ],
  "flair_380": [
    "A",
    "nLA",
    "Les",
    "A",
    "Ioten",
    "Indiens"
  ],
  "flair_381": [
    "Amerique",
    "Francais"
  ],
  "flair_382": [
    "A"
  ],
  "flair_383": [
    "Quebec"
  ],
  "flair_384": [],
  "flair_385": [
    "I"
  ],
  "flair_386": [
    "Virginie",
    "Versailles"
  ],
  "flair_387": [
    "Indiens."
  ],
  "flair_388": [
    "Indiens",
    "d'Ange",
    "Saut"
  ],
  "flair_389": [],
  "flair_390": [],
  "flair_391": [
    "Iit"
  ],
  "flair_392": [],
  "flair_393": [
    "Indiens",
    "Indiens",
    "Poscrit"
  ],
  "flair_394": [
    "Ie"
  ],
  "flair_395": [
    "Cette",
    "nLA"
  ],
  "flair_396": [
    "Paris"
  ],
  "flair_397": [
    "Indiens",
    "A"
  ],
  "flair_398": [
    "Ioret"
  ],
  "flair_399": [
    "A",
    "Grigny",
    "Canadien"
  ],
  "flair_400": [
    "Indiens",
    "Europeens"
  ],
  "flair_401": [
    "Indien",
    "Indien",
    "Loups-Hurons."
  ],
  "flair_402": [],
  "flair_403": [
    "A"
  ],
  "flair_404": [],
  "flair_405": [
    "A",
    "Indiens"
  ],
  "flair_406": [
    "nIL",
    "Angele",
    "Indiens"
  ],
  "flair_407": [
    "Indiens",
    "Grigny"
  ],
  "flair_408": [
    "Indiens"
  ],
  "flair_409": [
    "Grigny"
  ],
  "flair_410": [],
  "flair_411": [
    "nLA",
    "Mlanonghahela",
    "Francais"
  ],
  "flair_412": [
    "Virginie",
    "Francais",
    "Grigny"
  ],
  "flair_413": [
    "Canadiens",
    "Indiens"
  ],
  "flair_414": [
    "Achives"
  ],
  "flair_415": [
    "Contre",
    "Anglais"
  ],
  "flair_416": [
    "Virginie"
  ],
  "flair_417": [
    "A",
    "I",
    "IVIEE"
  ],
  "flair_418": [
    "Europe"
  ],
  "flair_419": [
    "nLA",
    "RIVIERE",
    "Francais"
  ],
  "flair_420": [
    "nLA",
    "Francais",
    "Francais"
  ],
  "flair_421": [
    "Indiens",
    "Indien"
  ],
  "flair_422": [
    "Canadiens",
    "Amerique"
  ],
  "flair_423": [
    "Europe.",
    "Nouvelle-Fance.",
    "Canada"
  ],
  "flair_424": [
    "Francais"
  ]
}